{
    "exercises": [
        {
            "catalogExerciseId": 613,
            "equipment": "Arm Blaster",
            "id": 422,
            "imageUrl": "https://39dd81ac8e96c60dc845b6b4fd1f3bf9.r2.cloudflarestorage.com/pow/arm-blaster-bicep-curl.gif?X-Amz-Algorithm=AWS4-HMAC-SHA256&X-Amz-Credential=140c882768e81c08c6afd2d1004ab296%2F20241223%2Fauto%2Fs3%2Faws4_request&X-Amz-Date=20241223T191750Z&X-Amz-Expires=3600&X-Amz-Signature=cbe82907c9ec67d4ac72d1bbcb0c0b1d54ce1449383e2ddddfd354c648170eb1&X-Amz-SignedHeaders=host&response-cache-control=public%2C%20max-age%3D86400%2C%20stale-while-revalidate%3D3600&response-content-type=image%2Fgif",
            "muscle": "Biceps",
            "muscleGroup": "Arm",
            "name": "Bicep Curl (Arm Blaster)",
            "order": 1,
            "sets": [Array
            ],
            "subcategory": "Upper Arm",
            "workoutId": 358
        }
    ],
    "id": 358,
    "isCompleted": false,
    "isStarted": false,
    "name": "Biceps",
    "order": 1,
    "programId": 290
}